MANIFEST.in
README.md
requirements.txt
setup.py
grpc_tracing/__init__.py
grpc_tracing/client_interceptor.py
grpc_tracing/jaeger_trace_client.py
grpc_tracing/server_interceptor.py
grpc_tracing/tags.py
python_grpc_tracing.egg-info/PKG-INFO
python_grpc_tracing.egg-info/SOURCES.txt
python_grpc_tracing.egg-info/dependency_links.txt
python_grpc_tracing.egg-info/requires.txt
python_grpc_tracing.egg-info/top_level.txt