Metadata-Version: 2.1
Name: python-grpc-tracing
Version: 0.1.5
Summary: Python gRPC jaeger tracing Interceptors
Home-page: https://github.com/kjlcl/python-grpc-tracing
Author: Liu Chongliang
Author-email: kjlcl@163.com
License: MIT
Platform: UNKNOWN
